{"sections":{"191794f6-0d82-46e8-9f75-a7c80df62259":{"type":"slideshow","blocks":{"template--19174806552914__191794f6-0d82-46e8-9f75-a7c80df62259-16876442735329694c-1":{"type":"image","disabled":true,"settings":{"text_position":"middle_center","subheading":"Tell your story","title":"Slide 2","button_1_text":"","button_1_link":"","button_2_text":"","button_2_link":"","text_color":"#ffffff","button_background":"#ffffff","button_text_color":"#000000","overlay_color":"#000000","overlay_opacity":30}}},"block_order":["template--19174806552914__191794f6-0d82-46e8-9f75-a7c80df62259-16876442735329694c-1"],"settings":{"section_height":"auto","transition_type":"sweep","autoplay":true,"cycle_speed":5,"background":"rgba(0,0,0,0)"}},"16971397964f31cb31":{"type":"apps","blocks":{"56252d4d-88eb-4d22-bfba-362e6ad8c699":{"type":"shopify:\/\/apps\/klaviyo-email-marketing-sms\/blocks\/form-embed-block\/2632fe16-c075-4321-a88b-50b567f42507","settings":{"formId":"RFFpRL"}}},"block_order":["56252d4d-88eb-4d22-bfba-362e6ad8c699"],"settings":{"include_horizontal_margins":false,"include_vertical_margins":false}},"a338d20c-8822-45c9-ba57-ca8d1eb766a8":{"type":"rich-text","settings":{"subheading":"","title":"Was benötige ich für den perfekten Kaffeegenuss?","content":"<ul><li><strong>Kaffee (es ist egal ob Vollautomat, Filtermaschine oder Instant Kaffee)<\/strong>, wir haben unsere Rezepte so angepasst das diese mit jedem Kaffee funktionieren.<\/li><li><strong>Tasse & Gläser <\/strong><\/li><li><strong>Verschiedene im Supermarkt erhältliche Zutaten <\/strong><\/li><li><strong>DrinkWhite™ Barista E-Book <\/strong><\/li><li><strong>Spaß & Freude etwas neues auszuprobieren <\/strong><\/li><\/ul>","button_text":"","button_link":"","background_type":"full_width","text_width":"fill","text_position":"center","text_alignment":"left","background":"rgba(0,0,0,0)","text_color":"rgba(0,0,0,0)","button_background":"rgba(0,0,0,0)","button_text_color":"rgba(0,0,0,0)"}},"66be21a3-2ea4-4dbd-ba1a-73498f794131":{"type":"rich-text","settings":{"subheading":"","title":"Was für Rezepte sind enthalten?","content":"<p>In dem DrinkWhite™ Barista E-Book sind insgesamt 100 von unserem Barista kreierte Rezepte enthalten die sich folgendermaßen auf <strong>über 200 Seiten<\/strong> aufgliedert: <\/p><ul><li><strong>37 Heißgetränke <\/strong><\/li><li><strong>25 Kaltgetränke <\/strong><\/li><li><strong>13 Cocktails <\/strong><\/li><li><strong>25 Backrezepte <\/strong><\/li><\/ul><p><\/p><p><\/p>","button_text":"","button_link":"","background_type":"full_width","text_width":"fill","text_position":"center","text_alignment":"left","background":"rgba(0,0,0,0)","text_color":"rgba(0,0,0,0)","button_background":"rgba(0,0,0,0)","button_text_color":"rgba(0,0,0,0)"}},"933b3b0c-39d7-489d-855b-53975aced6e2":{"type":"gallery","blocks":{"template--19913190080850__933b3b0c-39d7-489d-855b-53975aced6e2-image-1":{"type":"image","settings":{"image":"shopify:\/\/shop_images\/15_0c385314-f69b-4b33-ad36-0dd2c6cbab98.png","caption":""}},"template--19913190080850__933b3b0c-39d7-489d-855b-53975aced6e2-image-2":{"type":"image","settings":{"image":"shopify:\/\/shop_images\/9_4963423a-bee7-48c3-9d3c-083d168c88df.png","caption":""}},"template--19913190080850__933b3b0c-39d7-489d-855b-53975aced6e2-image-3":{"type":"image","settings":{"image":"shopify:\/\/shop_images\/14_6df9f27e-abd1-4f33-bc1c-12925f8ac578.png","caption":""}},"ce576dd2-e6d5-4092-a267-8fe29e28bef6":{"type":"image","settings":{"image":"shopify:\/\/shop_images\/7_452cfdec-6959-4975-8ad8-6d2ff0978a3f.png","caption":""}},"e3d34f73-77ae-4638-b0b7-7fe39c37d797":{"type":"image","settings":{"image":"shopify:\/\/shop_images\/26_392bfca2-a900-42b4-9e8a-78ffc6a9703d.png","caption":""}}},"block_order":["template--19913190080850__933b3b0c-39d7-489d-855b-53975aced6e2-image-1","template--19913190080850__933b3b0c-39d7-489d-855b-53975aced6e2-image-2","template--19913190080850__933b3b0c-39d7-489d-855b-53975aced6e2-image-3","ce576dd2-e6d5-4092-a267-8fe29e28bef6","e3d34f73-77ae-4638-b0b7-7fe39c37d797"],"settings":{"subheading":"","title":"","show_arrows":true,"background":"#f5f0e9","text_color":"rgba(0,0,0,0)"}},"b9bd6c1f-fb50-4960-ac97-6e0ec5bd119e":{"type":"rich-text","settings":{"subheading":"","title":"Was können Sie von diesem E-Book erwarten?","content":"<p>In diesem E-Book haben wir eine Vielzahl von leicht umsetzbaren Rezepten zusammengestellt, die von unserem Barista Tom weiter verfeinert wurden. Unser Ziel ist es, Ihnen neue Möglichkeiten zu bieten, Ihren Kaffeealltag aufzufrischen.<\/p><p> So müssen Sie nicht immer das Gleiche trinken, sondern können durch unsere Vorschläge Abwechslung genießen. <\/p><p><strong>Mit dem Mehrwert, den dieses E-Book bietet, werden Sie sicherlich Ihre Freunde beeindrucken und überraschen.<\/strong><\/p>","button_text":"","button_link":"","background_type":"full_width","text_width":"fill","text_position":"center","text_alignment":"left","background":"rgba(0,0,0,0)","text_color":"rgba(0,0,0,0)","button_background":"rgba(0,0,0,0)","button_text_color":"rgba(0,0,0,0)"}},"1697143179bf2c2a39":{"type":"apps","blocks":{"3fb4b5a1-d2eb-4eb2-9f7d-c36529cc79aa":{"type":"shopify:\/\/apps\/klaviyo-email-marketing-sms\/blocks\/form-embed-block\/2632fe16-c075-4321-a88b-50b567f42507","settings":{"formId":"RFFpRL"}}},"block_order":["3fb4b5a1-d2eb-4eb2-9f7d-c36529cc79aa"],"settings":{"include_horizontal_margins":false,"include_vertical_margins":false}},"57e79900-2718-4df0-9ec9-eda91ee83359":{"type":"rich-text","settings":{"subheading":"","title":"Warum bieten wir das E-Book kostenlos an?","content":"<p>Es gibt mehrere Gründe dafür. Zunächst hat unser Gründer Bodo dies aus Überzeugung so entschieden. Er glaubt fest daran, dass Wissen geteilt werden sollte, besonders wenn es darum geht, die Leidenschaft für Kaffee zu fördern. Zweitens, obwohl wir das E-Book normalerweise in unserem Online-Shop für 24,99€ verkaufen, befinden wir uns in einer entscheidenden Phase unseres Startups. <\/p><p>Wir möchten nicht nur unsere Marke stärken, sondern auch das Vertrauen und die Loyalität unserer Community aufbauen. Ein kostenfreies E-Book ist eine kleine Geste, um unsere Wertschätzung zu zeigen und gleichzeitig Feedback zu sammeln, das uns hilft, uns weiterzuentwickeln. Daher können Sie das E-Book aktuell auf dieser Seite völlig kostenfrei herunterladen und uns dabei helfen, gemeinsam zu wachsen.<\/p>","button_text":"","button_link":"","background_type":"full_width","text_width":"fill","text_position":"center","text_alignment":"left","background":"rgba(0,0,0,0)","text_color":"rgba(0,0,0,0)","button_background":"rgba(0,0,0,0)","button_text_color":"rgba(0,0,0,0)"}},"0ab20521-1cff-400a-b005-ffbc2febfd27":{"type":"rich-text","settings":{"subheading":"","title":"Wie lange bleibt dieses Angebot erhältlich?","content":"<p>Dieses Angebot können Sie nur über diesen Link nutzen und wird schon in wenigen Wochen kostenpflichtig sein.<\/p>","button_text":"","button_link":"","background_type":"full_width","text_width":"fill","text_position":"center","text_alignment":"left","background":"rgba(0,0,0,0)","text_color":"rgba(0,0,0,0)","button_background":"rgba(0,0,0,0)","button_text_color":"rgba(0,0,0,0)"}},"0494724c-4e2c-4b54-9c3d-776982034821":{"type":"rich-text","settings":{"subheading":"","title":"Wie erhalte ich das E-Book \"100 Barista Rezepte\" jetzt kostenfrei?","content":"<p>Geben Sie einfach Ihre E-Mail-Adresse in das untenstehende Feld ein, und wir senden Ihnen umgehend das E-Book zu, sodass Sie es direkt nutzen können.<\/p>","button_text":"","button_link":"","background_type":"full_width","text_width":"fill","text_position":"center","text_alignment":"left","background":"rgba(0,0,0,0)","text_color":"rgba(0,0,0,0)","button_background":"rgba(0,0,0,0)","button_text_color":"rgba(0,0,0,0)"}},"main":{"type":"main-page","disabled":true,"settings":{"show_title":false,"page_width":"medium"}},"16971439486a280648":{"type":"apps","blocks":{"bacacdb4-95cc-4659-9607-c4ed8e146248":{"type":"shopify:\/\/apps\/loox-product-reviews-photos\/blocks\/loox-trust-badge\/5c3b337f-fd14-4df5-b1d6-80ec13e6e28e","settings":{"layout":"horizontal-slim-star","alignment":"fillContainer","scheme-type":"inverted","review-title":"reviews","rating-icon":true,"average-rating":true,"review-count":true,"open-reviews":false,"show-border":false,"border-radius":0,"font-size":20,"background-color":"","secondary-background-color":"","text-color":"","rating-icon-color":"","border-color":""}}},"block_order":["bacacdb4-95cc-4659-9607-c4ed8e146248"],"settings":{"include_horizontal_margins":true,"include_vertical_margins":true}},"c3518489-22a2-47c1-8621-c271fa691ded":{"type":"rich-text","disabled":true,"settings":{"subheading":"","title":"5 Gründe, warum DrinkWhite Kaffeekonzentrat besser ist als andere  ❤️","content":"","button_text":"","button_link":"","background_type":"full_width","text_width":"fill","text_position":"center","text_alignment":"left","background":"rgba(0,0,0,0)","text_color":"rgba(0,0,0,0)","button_background":"rgba(0,0,0,0)","button_text_color":"rgba(0,0,0,0)"}},"fe548d8a-d129-4a0a-a4d4-4fc334433ccb":{"type":"slideshow","blocks":{"381d3749-00a7-4dbb-96dc-edd5c5e8ec7b":{"type":"image","disabled":true,"settings":{"image":"shopify:\/\/shop_images\/Bildschirmfoto_2023-06-25_um_00.41.06.png","mobile_image":"shopify:\/\/shop_images\/Bildschirmfoto_2023-06-25_um_00.41.06.png","text_position":"middle_center","subheading":"","title":"","button_1_text":"","button_1_link":"","button_2_text":"","button_2_link":"","text_color":"#ffffff","button_background":"#ffffff","button_text_color":"#000000","overlay_color":"#000000","overlay_opacity":0}}},"block_order":["381d3749-00a7-4dbb-96dc-edd5c5e8ec7b"],"settings":{"section_height":"auto","transition_type":"sweep","autoplay":false,"cycle_speed":4,"background":"rgba(0,0,0,0)"}},"11610341-5654-4fb4-bede-0b140eca501f":{"type":"custom-html","settings":{"subheading":"","title":"","html":"<style>\n.announcement-bar, .header__inline-navigation,.header__secondary-links {\ndisplay:none;\n}\n\n.header__wrapper {\n    justify-content: center;\n}\n<\/style>","add_vertical_spacing":false,"background_type":"full_width","background":"rgba(0,0,0,0)","text_color":"rgba(0,0,0,0)"}},"4dbfff4d-700d-4dff-9416-31c57f5dc0bf":{"type":"rich-text","disabled":true,"custom_css":["@media only screen and (max-width: 690px) {.button--primary {position: fixed; bottom: 10px; width: 200px; \/* adjust as needed *\/ left: 50%; margin-left: -100px; }}"],"settings":{"subheading":"","title":"","content":"","button_text":"jetzt kaufen","button_link":"shopify:\/\/products\/drinkwhite-kaffeekonzentrat","background_type":"full_width","text_width":"fill","text_position":"center","text_alignment":"center","background":"#ffffff","text_color":"rgba(0,0,0,0)","button_background":"#f6a429","button_text_color":"rgba(0,0,0,0)"}},"896dab17-164c-4ee9-a3f6-c3f20fc07b1d":{"type":"video","disabled":true,"settings":{"subheading":"","title":"","video_url":"https:\/\/www.youtube.com\/watch?v=_9VUPq3SxOc","background_type":"full_width","video_size":"auto","autoplay":true,"show_video_controls":false,"background":"rgba(0,0,0,0)","text_color":"rgba(0,0,0,0)"}},"169714309543f4aea5":{"type":"apps","blocks":{"ef7d52f4-2047-442b-bcca-43864a8b9965":{"type":"shopify:\/\/apps\/klaviyo-email-marketing-sms\/blocks\/form-embed-block\/2632fe16-c075-4321-a88b-50b567f42507","settings":{"formId":"RFFpRL"}}},"block_order":["ef7d52f4-2047-442b-bcca-43864a8b9965"],"settings":{"include_horizontal_margins":false,"include_vertical_margins":false}},"6e92a441-44ca-4aec-93e2-eec0eaee6d4d":{"type":"image-with-text","blocks":{"template--19913190080850__6e92a441-44ca-4aec-93e2-eec0eaee6d4d-item-1":{"type":"item","settings":{"image":"shopify:\/\/shop_images\/Team_DrinkWhite.png","tab_label":"Item","subheading":"","title":"Das Team hinter \"100 Barista Rezepte\"","content":"<p>Sie fragen sich sicherlich, wer die kreativen Köpfe hinter \"100 Barista Rezepte\" sind. Lassen Sie uns das Geheimnis lüften: Das engagierte Team von DrinkWhite™ hat diese Sammlung für Sie zusammengestellt. <\/p><p>DrinkWhite™ ist nicht nur ein weiteres Startup im Kaffeebereich. Unsere Mission ist es, den Kaffeegenuss durch innovative Ansätze und Einfachheit zu revolutionieren. Wir glauben, dass jeder, unabhängig von seiner Erfahrung oder Ausrüstung, in den Genuss von erstklassigem Kaffee kommen sollte. Deshalb bieten wir nicht nur hochwertige Produkte an, sondern auch Ressourcen wie dieses E-Book. <\/p><p>Selbst wenn Sie kein DrinkWhite™-Produkt besitzen, möchten wir, dass Sie die Vielfalt und den Reichtum des Kaffees entdecken. Unsere Leidenschaft für Kaffee treibt uns an, und wir hoffen, dass Sie diese durch unsere sorgfältig ausgewählten Rezepte teilen können.<\/p>","button_text":"","button_link":""}}},"block_order":["template--19913190080850__6e92a441-44ca-4aec-93e2-eec0eaee6d4d-item-1"],"settings":{"reveal_on_scroll":true,"background_type":"full_width","background_overlap":"image","image_position":"left","text_alignment":"left","cycle_speed":8,"accent_background":"#f5f0e9","text_color":"rgba(0,0,0,0)","button_background":"rgba(0,0,0,0)","button_text_color":"rgba(0,0,0,0)"}}},"order":["191794f6-0d82-46e8-9f75-a7c80df62259","16971397964f31cb31","a338d20c-8822-45c9-ba57-ca8d1eb766a8","66be21a3-2ea4-4dbd-ba1a-73498f794131","933b3b0c-39d7-489d-855b-53975aced6e2","b9bd6c1f-fb50-4960-ac97-6e0ec5bd119e","1697143179bf2c2a39","57e79900-2718-4df0-9ec9-eda91ee83359","0ab20521-1cff-400a-b005-ffbc2febfd27","0494724c-4e2c-4b54-9c3d-776982034821","main","16971439486a280648","c3518489-22a2-47c1-8621-c271fa691ded","fe548d8a-d129-4a0a-a4d4-4fc334433ccb","11610341-5654-4fb4-bede-0b140eca501f","4dbfff4d-700d-4dff-9416-31c57f5dc0bf","896dab17-164c-4ee9-a3f6-c3f20fc07b1d","169714309543f4aea5","6e92a441-44ca-4aec-93e2-eec0eaee6d4d"]}